deltakit/__init__.py
deltakit/py.typed
deltakit/circuit/__init__.py
deltakit/circuit/gates/__init__.py
deltakit/circuit/noise_channels/__init__.py
deltakit/core/__init__.py
deltakit/core/data_formats/__init__.py
deltakit/core/decoding_graphs/__init__.py
deltakit/core/plotting/__init__.py
deltakit/core/plotting/colours.py
deltakit/decode/__init__.py
deltakit/decode/analysis/__init__.py
deltakit/decode/noise_sources/__init__.py
deltakit/decode/utils/__init__.py
deltakit/explorer/__init__.py
deltakit/explorer/analysis/__init__.py
deltakit/explorer/codes/__init__.py
deltakit/explorer/data/__init__.py
deltakit/explorer/enums/__init__.py
deltakit/explorer/plotting/__init__.py
deltakit/explorer/qpu/__init__.py
deltakit/explorer/simulation/__init__.py
deltakit/explorer/types/__init__.py
deltakit-0.6.2.dist-info/licenses/LICENSE
deltakit-0.6.2.dist-info/METADATA
deltakit-0.6.2.dist-info/WHEEL
deltakit-0.6.2.dist-info/top_level.txt
deltakit-0.6.2.dist-info/RECORD
