Metadata-Version: 2.4
Name: deltakit
Version: 0.6.2
Summary: A Python toolkit to enable users with the design and execution of quantum error correction (QEC) experiments.
Author-email: Deltakit Team <deltakit@riverlane.com>
License-Expression: Apache-2.0
Project-URL: Homepage, https://github.com/Deltakit/deltakit
Project-URL: Source, https://github.com/Deltakit/deltakit
Project-URL: Documentation, https://deltakit.riverlane.com/
Project-URL: Issues, https://github.com/Deltakit/deltakit/issues
Project-URL: Changelog, https://github.com/Deltakit/deltakit/releases
Classifier: Development Status :: 3 - Alpha
Classifier: Intended Audience :: Science/Research
Classifier: Intended Audience :: Developers
Classifier: Operating System :: OS Independent
Classifier: Programming Language :: Python
Classifier: Programming Language :: Python :: 3
Classifier: Programming Language :: Python :: 3 :: Only
Classifier: Programming Language :: Python :: 3.10
Classifier: Programming Language :: Python :: 3.11
Classifier: Programming Language :: Python :: 3.12
Classifier: Programming Language :: Python :: 3.13
Classifier: Programming Language :: Python :: Implementation :: CPython
Classifier: Topic :: Scientific/Engineering
Classifier: Topic :: Scientific/Engineering :: Quantum Computing
Classifier: Typing :: Typed
Requires-Python: <3.14,>=3.10
License-File: LICENSE
Requires-Dist: deltakit-circuit~=0.6
Requires-Dist: deltakit-core~=0.6
Requires-Dist: deltakit-decode~=0.6
Requires-Dist: deltakit-explorer~=0.6
Dynamic: license-file
